sqlitesec/__init__.py
sqlitesec-1.0.0.dist-info/licenses/LICENSE
sqlitesec-1.0.0.dist-info/METADATA
sqlitesec-1.0.0.dist-info/WHEEL
sqlitesec-1.0.0.dist-info/top_level.txt
sqlitesec-1.0.0.dist-info/RECORD
