Metadata-Version: 2.4
Name: sqlitesec
Version: 1.0.0
Summary: Secure SQLite databases with AES-256 encryption
Author-email: John Doe <pypideveloperaccount.rejoicing466@passmail.net>
Maintainer-email: John Doe <pypideveloperaccount.rejoicing466@passmail.net>
License: MIT
Project-URL: Homepage, https://github.com/oyvinrog/sqlitesec
Project-URL: Documentation, https://github.com/oyvinrog/sqlitesec#readme
Project-URL: Repository, https://github.com/oyvinrog/sqlitesec.git
Project-URL: Issues, https://github.com/oyvinrog/sqlitesec/issues
Keywords: sqlite,encryption,security,database,aes
Classifier: Development Status :: 4 - Beta
Classifier: Intended Audience :: Developers
Classifier: Operating System :: OS Independent
Classifier: Programming Language :: Python :: 3
Classifier: Programming Language :: Python :: 3.8
Classifier: Programming Language :: Python :: 3.9
Classifier: Programming Language :: Python :: 3.10
Classifier: Programming Language :: Python :: 3.11
Classifier: Programming Language :: Python :: 3.12
Classifier: Topic :: Database
Classifier: Topic :: Security :: Cryptography
Classifier: Topic :: Software Development :: Libraries :: Python Modules
Requires-Python: >=3.8
License-File: LICENSE
Requires-Dist: cryptography>=3.0.0
Dynamic: license-file
